sledo/__init__.py
sledo/__main__.py
sledo/main.py
sledo/generate/__init__.py
sledo/generate/config.py
sledo/generate/field_generators/__init__.py
sledo/generate/field_generators/base.py
sledo/generate/field_generators/country.py
sledo/generate/field_generators/date.py
sledo/generate/field_generators/name.py
sledo/generate/field_generators/number.py
sledo/generate/field_generators/reference.py
sledo/generate/field_generators/schema.py
sledo-0.2.3.dist-info/LICENSE
sledo-0.2.3.dist-info/METADATA
sledo-0.2.3.dist-info/WHEEL
sledo-0.2.3.dist-info/entry_points.txt
sledo-0.2.3.dist-info/top_level.txt
sledo-0.2.3.dist-info/RECORD
