Metadata-Version: 2.1
Name: sledo
Version: 0.2.3
Summary: A simple demodata generator for the command-line.
Home-page: https://github.com/luxbe/sledo
Author: luxbe, Jakob, Ammar, Melli, Deniz, Larissa
Author-email: luxbe@tutanota.com, jakobjonathan@aol.com, ammar@begovic.eu, melina.petersen99@web.de, denizcan.1999er@gmail.com, larissac0504@gmail.com
License: MIT
Platform: UNKNOWN
Classifier: Programming Language :: Python :: 3
Classifier: Operating System :: OS Independent
License-File: LICENSE
Requires-Dist: click
Requires-Dist: pyyaml
Requires-Dist: schema
